adiona_mcp/__init__.py
adiona_mcp/server.py
adiona_mcp-0.1.1.dist-info/METADATA
adiona_mcp-0.1.1.dist-info/WHEEL
adiona_mcp-0.1.1.dist-info/entry_points.txt
adiona_mcp-0.1.1.dist-info/RECORD
