Metadata-Version: 2.4
Name: adiona-mcp
Version: 0.1.1
Summary: Let LLM use adiona mcp tools to search locations hotels etc
Author-email: Biki Das <36537203+bikidsx@users.noreply.github.com>
Requires-Python: >=3.13
Requires-Dist: fastmcp
Requires-Dist: httpx
Requires-Dist: mcp
Requires-Dist: python-dotenv
